{"AUD":["AUD","10402.00","10730.00"],"CAD":["CAD","10456.00","10725.00"],"CHF":["CHF","13566.00","14066.00"],"CNY":["CNY","1948.00","2041.00"],"DKK":["DKK","2030.00","2197.00"],"EUR":["EUR","15520.00","15893.00"],"GBP":["GBP","16959.00","17352.00"],"HKD":["HKD","1640.00","1760.00"],"JPY":["JPY","119.68","123.82"],"NOK":["NOK","1610.00","1760.00"],"NZD":["NZD","9600.00","9889.00"],"SAR":["SAR","3396.00","3702.00"],"SEK":["SEK","1596.00","1700.00"],"SGD":["SGD","9636.00","9900.00"],"USD":["USD","13190.00","13390.00"],"Jumlah":["Jumlah","Dari","(Kurs)","Ke","(Kurs)","Hasil"],"":[""]}